encpoly/__init__.py
encpoly/codec.py
encpoly-0.2.0.dist-info/WHEEL
encpoly-0.2.0.dist-info/METADATA
encpoly-0.2.0.dist-info/RECORD
